mortal_bases/__init__.py
mortal_bases/base_main.cpython-312-x86_64-linux-gnu.so
mortal_bases/bases/__init__.py
mortal_bases/bases/auth_base.cpython-312-x86_64-linux-gnu.so
mortal_bases/bases/callable_base.cpython-312-x86_64-linux-gnu.so
mortal_bases/bases/common_base.cpython-312-x86_64-linux-gnu.so
mortal_bases/bases/decorator_base.cpython-312-x86_64-linux-gnu.so
mortal_bases/bases/dict_base.cpython-312-x86_64-linux-gnu.so
mortal_bases/bases/list_base.cpython-312-x86_64-linux-gnu.so
mortal_bases/bases/path_base.cpython-312-x86_64-linux-gnu.so
mortal_bases/bases/time_base.cpython-312-x86_64-linux-gnu.so
mortal_bases-4.6.0.dist-info/METADATA
mortal_bases-4.6.0.dist-info/WHEEL
mortal_bases-4.6.0.dist-info/top_level.txt
mortal_bases-4.6.0.dist-info/RECORD
